GeoOpPackage/OneDdistance.py
GeoOpPackage/__init__.py
GeoOpPackage/arcLen.py
GeoOpPackage/centAngle.py
GeoOpPackage/circArea.py
GeoOpPackage/circum.py
GeoOpPackage/coneArea.py
GeoOpPackage/cubeArea.py
GeoOpPackage/cuboidArea.py
GeoOpPackage/cylArea.py
GeoOpPackage/polPeri.py
GeoOpPackage/pyrSurfArea.py
GeoOpPackage/pyrVol.py
GeoOpPackage/slope.py
GeoOpPackage/sphArea.py
GeoOpPackage/sumInterior.py
geooppackage-0.0.5.dist-info/METADATA
geooppackage-0.0.5.dist-info/WHEEL
geooppackage-0.0.5.dist-info/licenses/license.txt
geooppackage-0.0.5.dist-info/RECORD
