Metadata-Version: 2.1
Name: GeoOpPackage
Version: 0.0.5
Summary: This is a python library that includes operations on all 1D, 2D and 3D Geometric shapes
Project-URL: Homepage, https://github.com/sherinnn/Geometric-Shapes-Package
Project-URL: Bug Tracker, https://github.com/pypa/sampleproject/issues
Author-email: Sherin Thomas <tsherin140@gmail.com>
License-File: license.txt
Classifier: License :: OSI Approved :: MIT License
Classifier: Operating System :: OS Independent
Classifier: Programming Language :: Python :: 3
Requires-Python: >=3.7
